mcp_server_notify/__init__.py
mcp_server_notify/__main__.py
mcp_server_notify/schemas.py
mcp_server_notify/server.py
mcp_server_notify/sound.py
mcp_server_notify-0.1.0.dist-info/METADATA
mcp_server_notify-0.1.0.dist-info/WHEEL
mcp_server_notify-0.1.0.dist-info/entry_points.txt
mcp_server_notify-0.1.0.dist-info/licenses/LICENSE
mcp_server_notify-0.1.0.dist-info/RECORD
